sensorfabric/__init__.py
sensorfabric/athena.py
sensorfabric/endpoints.py
sensorfabric/mdh.py
sensorfabric/needle.py
sensorfabric/utils.py
sensorfabric-2.0.3.dist-info/LICENSE
sensorfabric-2.0.3.dist-info/METADATA
sensorfabric-2.0.3.dist-info/WHEEL
sensorfabric-2.0.3.dist-info/top_level.txt
sensorfabric-2.0.3.dist-info/RECORD
