Metadata-Version: 2.1
Name: sensorfabric
Version: 2.0.3
Summary: Python library for UA Sensor Fabric
Home-page: https://github.com/UArizonaCB2/sensorfabric-py.git
Author: Shravan Aras
Author-email: shravanaras@arizona.edu
License: MIT
Keywords: sensors sensorfabric
Requires-Python: >=3
License-File: LICENSE
Requires-Dist: boto3 ==1.28.49
Requires-Dist: pandas ==2.1.0
Requires-Dist: numpy ==1.25.2
Requires-Dist: pyjwt ==2.8.0
Requires-Dist: configparser ==6.0.0
Requires-Dist: pathlib ==1.0.1
Requires-Dist: cryptography ==41.0.4
Requires-Dist: requests ==2.31.0
